<?xml version="1.0" encoding="utf-8" ?><dwsync><file name="JosefinSans-BoldItalic.css" server="Macintosh HD/Applications/MAMP/htdocs/acanto/" local="3556512014" remote="3556512014" Dst="-1" /><file name="JosefinSans-BoldItalic.eot" server="Macintosh HD/Applications/MAMP/htdocs/acanto/" local="3556512014" remote="3556512014" Dst="-1" /><file name="JosefinSans-BoldItalic.html" server="Macintosh HD/Applications/MAMP/htdocs/acanto/" local="3556512014" remote="3556512014" Dst="-1" /><file name="JosefinSans-BoldItalic.svg" server="Macintosh HD/Applications/MAMP/htdocs/acanto/" local="3556512014" remote="3556512014" Dst="-1" /><file name="JosefinSans-BoldItalic.ttf" server="Macintosh HD/Applications/MAMP/htdocs/acanto/" local="3556512013" remote="3556512013" Dst="-1" /><file name="JosefinSans-BoldItalic.woff" server="Macintosh HD/Applications/MAMP/htdocs/acanto/" local="3556512014" remote="3556512014" Dst="-1" /><file name="JosefinSans-LightItalic.css" server="Macintosh HD/Applications/MAMP/htdocs/acanto/" local="3556512011" remote="3556512011" Dst="-1" /><file name="JosefinSans-LightItalic.eot" server="Macintosh HD/Applications/MAMP/htdocs/acanto/" local="3556512011" remote="3556512011" Dst="-1" /><file name="JosefinSans-LightItalic.html" server="Macintosh HD/Applications/MAMP/htdocs/acanto/" local="3556512011" remote="3556512011" Dst="-1" /><file name="JosefinSans-LightItalic.svg" server="Macintosh HD/Applications/MAMP/htdocs/acanto/" local="3556512011" remote="3556512011" Dst="-1" /><file name="JosefinSans-LightItalic.ttf" server="Macintosh HD/Applications/MAMP/htdocs/acanto/" local="3556512011" remote="3556512011" Dst="-1" /><file name="JosefinSans-LightItalic.woff" server="Macintosh HD/Applications/MAMP/htdocs/acanto/" local="3556512011" remote="3556512011" Dst="-1" /><file name="JosefinSans-Thin.css" server="Macintosh HD/Applications/MAMP/htdocs/acanto/" local="3556512011" remote="3556512011" Dst="-1" /><file name="JosefinSans-Thin.eot" server="Macintosh HD/Applications/MAMP/htdocs/acanto/" local="3556512011" remote="3556512011" Dst="-1" /><file name="JosefinSans-Thin.html" server="Macintosh HD/Applications/MAMP/htdocs/acanto/" local="3556512011" remote="3556512011" Dst="-1" /><file name="JosefinSans-Thin.svg" server="Macintosh HD/Applications/MAMP/htdocs/acanto/" local="3556512011" remote="3556512011" Dst="-1" /><file name="JosefinSans-Thin.ttf" server="Macintosh HD/Applications/MAMP/htdocs/acanto/" local="3556512010" remote="3556512010" Dst="-1" /><file name="JosefinSans-Thin.woff" server="Macintosh HD/Applications/MAMP/htdocs/acanto/" local="3556512011" remote="3556512011" Dst="-1" /><file name="JosefinSans-Thin1.css" server="Macintosh HD/Applications/MAMP/htdocs/acanto/" local="3556512011" remote="3556512011" Dst="-1" /><file name="JosefinSans-Thin1.eot" server="Macintosh HD/Applications/MAMP/htdocs/acanto/" local="3556512011" remote="3556512011" Dst="-1" /><file name="JosefinSans-Thin1.html" server="Macintosh HD/Applications/MAMP/htdocs/acanto/" local="3556512011" remote="3556512011" Dst="-1" /><file name="JosefinSans-Thin1.svg" server="Macintosh HD/Applications/MAMP/htdocs/acanto/" local="3556512011" remote="3556512011" Dst="-1" /><file name="JosefinSans-Thin1.ttf" server="Macintosh HD/Applications/MAMP/htdocs/acanto/" local="3556512011" remote="3556512011" Dst="-1" /><file name="JosefinSans-Thin1.woff" server="Macintosh HD/Applications/MAMP/htdocs/acanto/" local="3556512011" remote="3556512011" Dst="-1" /></dwsync>